upils/__init__.py
upils/datetime.py
upils/iterable.py
upils/list.py
upils/logging.py
upils/slate_converter.py
upils/string.py
upils-0.11.0.dist-info/METADATA
upils-0.11.0.dist-info/WHEEL
upils-0.11.0.dist-info/RECORD
