Metadata-Version: 2.4
Name: upils
Version: 0.11.0
Summary: Unified Python Utils. Requires python 3.10 and later
Author: Aslam Hadi Harsono
Author-email: aslam.hadi@kumparan.com
Requires-Python: >=3.10,<4.0
Classifier: Programming Language :: Python :: 3
Classifier: Programming Language :: Python :: 3.10
Classifier: Programming Language :: Python :: 3.11
Classifier: Programming Language :: Python :: 3.12
Classifier: Programming Language :: Python :: 3.13
Classifier: Programming Language :: Python :: 3.14
Requires-Dist: loguru (>=0.7.2,<0.8.0)
Requires-Dist: pytz (>=2022.1,<2023.0)
